auto_cnn/__init__.py
auto_cnn/cnn_structure.py
auto_cnn/gan.py
auto_cnn-1.0.dist-info/LICENSE
auto_cnn-1.0.dist-info/METADATA
auto_cnn-1.0.dist-info/WHEEL
auto_cnn-1.0.dist-info/top_level.txt
auto_cnn-1.0.dist-info/RECORD
