Metadata-Version: 2.1
Name: auto-cnn
Version: 1.0
Summary: Automatically designing CNN architectures using Genetic Algorithm for Image Classification implementation
Home-page: https://github.com/Marius-Juston/AutoCNN
Author: Marius Juston
Author-email: marius.juston@hotmail.fr
License: UNKNOWN
Platform: UNKNOWN
Classifier: Programming Language :: Python :: 3
Classifier: License :: OSI Approved :: MIT License
Classifier: Operating System :: OS Independent
Classifier: Intended Audience :: Developers
Classifier: Intended Audience :: Science/Research
Classifier: Programming Language :: Python :: 3.8
Classifier: Topic :: Scientific/Engineering :: Artificial Intelligence
Classifier: Topic :: Scientific/Engineering
Classifier: Topic :: Scientific/Engineering :: Image Recognition
Classifier: Topic :: Scientific/Engineering :: Image Processing
Requires-Python: >=3.6
Requires-Dist: tensorflow (>=2.0.0)
